clifresh.py
setup.py
clifresh.egg-info/PKG-INFO
clifresh.egg-info/SOURCES.txt
clifresh.egg-info/dependency_links.txt
clifresh.egg-info/entry_points.txt
clifresh.egg-info/requires.txt
clifresh.egg-info/top_level.txt
clifresh.egg-info/zip-safe