Metadata-Version: 1.0
Name: clifresh
Version: 5
Summary: A tool for logging time in the freshbooks invoice service.
Home-page: http://github.com/nickgartmann/clifresh/
Author: Nick Gartmann
Author-email: nick@rokkincat.com
License: BSD
Platform: any
Classifier: Intended Audience :: Developers
Classifier: License :: OSI Approved :: BSD License
Classifier: Operating System :: OS Independent
Classifier: Programming Language :: Python
